pybrary/__init__.py
pybrary/ascii.py
pybrary/command.py
pybrary/commander.py
pybrary/commandparams.py
pybrary/commands.py
pybrary/config.py
pybrary/contract.py
pybrary/dico.py
pybrary/fernet.py
pybrary/files.py
pybrary/func.py
pybrary/fuzzy.py
pybrary/htmllib.py
pybrary/httplib.py
pybrary/logger.py
pybrary/main.py
pybrary/makelib.py
pybrary/model_base.py
pybrary/model_plus.py
pybrary/modules.py
pybrary/net.py
pybrary/primes.py
pybrary/refiles.py
pybrary/rex.py
pybrary/shell.py
pybrary/ssh.py
pybrary/statefull.py
pybrary/svg.py
pybrary/tracer.py
pybrary/utils.py
pybrary/compat/__init__.py
pybrary/compat/re.py
pybrary/compat/warnings.py
pybrary/compat/backport/__init__.py
pybrary/compat/backport/warnings.py
pybrary-0.2601.0.dist-info/METADATA
pybrary-0.2601.0.dist-info/WHEEL
pybrary-0.2601.0.dist-info/entry_points.txt
pybrary-0.2601.0.dist-info/top_level.txt
pybrary-0.2601.0.dist-info/RECORD
