Metadata-Version: 2.4
Name: pybrary
Version: 0.2601.0
Summary: Python Library
Author-email: Louis RIVIERE <louis@riviere.xyz>
License: MIT
Project-URL: pypi, https://pypi.org/project/pybrary
Project-URL: repository, https://gitlab.com/dugres/pybrary
Keywords: library
Classifier: Development Status :: 3 - Alpha
Classifier: License :: OSI Approved :: MIT License
Classifier: Programming Language :: Python :: 3
Classifier: Operating System :: POSIX :: Linux
Classifier: Environment :: Console
Classifier: Intended Audience :: Developers
Requires-Python: >=3.9
Requires-Dist: cryptography
Requires-Dist: nicely
Provides-Extra: dev
Requires-Dist: pytest; extra == "dev"
